LICENSE.txt
README.md
setup.cfg
setup.py
mlwrapper/__init__.py
mlwrapper/mlwrapper.py
mlwrapper.egg-info/PKG-INFO
mlwrapper.egg-info/SOURCES.txt
mlwrapper.egg-info/dependency_links.txt
mlwrapper.egg-info/requires.txt
mlwrapper.egg-info/top_level.txt
mlwrapper/tests/__init__.py
mlwrapper/tests/tests_mlwrapper.py