Metadata-Version: 2.1
Name: mlwrapper
Version: 0.1
Summary: Wrapper for machine learning experiments
Home-page: https://github.com/SlavicMate/mlwrapper
Author: Albert Swiecicki
Author-email: albertswiecicki@gmail.com
License: MIT
Download-URL: https://github.com/SlavicMate/mlwrapper/archive/v0.1.0.tar.gz
Platform: UNKNOWN
Classifier: Development Status :: 3 - Alpha
Classifier: Intended Audience :: Developers
Classifier: License :: OSI Approved :: MIT License
Classifier: Topic :: Scientific/Engineering :: Artificial Intelligence
Classifier: Programming Language :: Python
Classifier: Programming Language :: Python :: 3
Classifier: Programming Language :: Python :: 3.6
Classifier: Programming Language :: Python :: 3.7
Classifier: Operating System :: OS Independent
Requires-Python: >=3.6
